[
    {
        "code": "AUD",
        "num": 36,
        "decimal": 2,
        "currency": "Australian Dollar",
        "locations": ["Australia", "Christmas Island", "Cocos (Keeling) Islands", "Heard Island and McDonald Islands", "Kiribati", "Nauru", "Norfolk Island", "Tuvalu"]
    },
    {
        "code": "BRL",
        "num": 986,
        "decimal": 2,
        "currency": "Brazilian Real",
        "locations": ["Brazil"]
    },
    {
        "code": "CAD",
        "num": 124,
        "decimal": 2,
        "currency": "Canadian Dollar",
        "locations": ["Canada"]
    },
    {
        "code": "CHF",
        "num": 756,
        "decimal": 2,
        "currency": "Swiss Franc",
        "locations": ["Switzerland", "Liechtenstein"]
    },
    {
        "code": "CNY",
        "num": 156,
        "decimal": 2,
        "currency": "Chinese Yuan Renminbi",
        "locations": ["China"]
    },
    {
        "code": "DKK",
        "num": 208,
        "decimal": 2,
        "currency": "Danish Krone",
        "locations": ["Denmark", "Faroe Islands", "Greenland"]
    },
    {
        "code": "EUR",
        "num": 978,
        "decimal": 2,
        "currency": "Euro",
        "locations": ["Eurozone countries"]
    },
    {
        "code": "GBP",
        "num": 826,
        "decimal": 2,
        "currency": "Pound Sterling",
        "locations": ["United Kingdom", "Jersey", "Guernsey", "Isle of Man", "South Georgia and the South Sandwich Islands", "British Antarctic Territory"]
    },
    {
        "code": "HKD",
        "num": 344,
        "decimal": 2,
        "currency": "Hong Kong Dollar",
        "locations": ["Hong Kong", "Macau"]
    },
    {
        "code": "HUF",
        "num": 348,
        "decimal": 2,
        "currency": "Hungarian Forint",
        "locations": ["Hungary"]
    },
    {
        "code": "INR",
        "num": 356,
        "decimal": 2,
        "currency": "Indian Rupee",
        "locations": ["India"]
    },
    {
        "code": "JPY",
        "num": 392,
        "decimal": 0,
        "currency": "Japanese Yen",
        "locations": ["Japan"]
    },
    {
        "code": "MXN",
        "num": 484,
        "decimal": 2,
        "currency": "Mexican Peso",
        "locations": ["Mexico"]
    },
    {
        "code": "MYR",
        "num": 458,
        "decimal": 2,
        "currency": "Malaysian Ringgit",
        "locations": ["Malaysia"]
    },
    {
        "code": "NOK",
        "num": 578,
        "decimal": 2,
        "currency": "Norwegian Krone",
        "locations": ["Norway", "Svalbard and Jan Mayen"]
    },
    {
        "code": "NZD",
        "num": 554,
        "decimal": 2,
        "currency": "New Zealand Dollar",
        "locations": ["New Zealand", "Cook Islands", "Niue", "Pitcairn Islands", "Tokelau"]
    },
    {
        "code": "PHP",
        "num": 608,
        "decimal": 2,
        "currency": "Philippine Peso",
        "locations": ["Philippines"]
    },
    {
        "code": "RUB",
        "num": 643,
        "decimal": 2,
        "currency": "Russian Ruble",
        "locations": ["Russia"]
    },
    {
        "code": "SEK",
        "num": 752,
        "decimal": 2,
        "currency": "Swedish Krona",
        "locations": ["Sweden"]
    },
    {
        "code": "SGD",
        "num": 702,
        "decimal": 2,
        "currency": "Singapore Dollar",
        "locations": ["Singapore", "Brunei"]
    },
    {
        "code": "THB",
        "num": 764,
        "decimal": 2,
        "currency": "Thai Baht",
        "locations": ["Thailand"]
    },
    {
        "code": "TRY",
        "num": 949,
        "decimal": 2,
        "currency": "Turkish Lira",
        "locations": ["Turkey"]
    },
    {
        "code": "USD",
        "num": 840,
        "decimal": 2,
        "currency": "US Dollar",
        "locations": ["United States", "American Samoa", "Bonaire", "British Indian Ocean Territory", "Ecuador", "El Salvador", "Guam", "Haiti", "Marshall Islands", "Micronesia", "Northern Mariana Islands", "Palau", "Panama", "Puerto Rico", "Timor-Leste", "Turks and Caicos Islands", "United States Minor Outlying Islands", "Virgin Islands (British)", "Virgin Islands (U.S.)"]
    },
    {
        "code": "ZAR",
        "num": 710,
        "decimal": 2,
        "currency": "South African Rand",
        "locations": ["South Africa", "Lesotho", "Namibia"]
    }
]
